{"Message": "7 reported faults", "TimestampUtc": "/Date(1618242314000)/", "Uri": "http://api.sse.com/powerdistribution/network/v3/api/faults/", "Faults": [{"Title": "DD11 Area", "Reference": "HB5880", "LoggedAtUtc": "/Date(1618240680000)/", "EstimatedFaultUpdateTimeUtc": "/Date(-62135596800000)/", "EstimatedArrivalOnSiteUtc": "/Date(1618245000000)/", "EstimatedRestorationTimeUtc": "/Date(1618250400000)/", "FaultType": "LV", "Location": {"Latitude": 56.57094789353572, "Longitude": -2.761456794171527, "DisplayText": "56.570947893535717, -2.7614567941715271"}, "Message": "We\u2019re sorry for the loss of supply. We currently have a fault affecting the areas listed. Our engineers are on site working hard to get the power back on as quickly as they can. If you need more information, please call us on 105 or send us a message on <a href=\"http://m.me/ssencommunity/\">Facebook</a> or Twitter (<a href=\"https://twitter.com/ssencommunity\">@ssencommunity</a>) and quote reference 'HB5880'", "AffectedAreas": ["DD11 2QY"], "DepotCode": "70", "IsDepot": false}, {"Title": "IV3 Area", "Reference": "HB5871", "LoggedAtUtc": "/Date(1618238820000)/", "EstimatedFaultUpdateTimeUtc": "/Date(-62135596800000)/", "EstimatedArrivalOnSiteUtc": "/Date(1618250400000)/", "EstimatedRestorationTimeUtc": "/Date(1618250100000)/", "FaultType": "LV", "Location": {"Latitude": 57.48037278994726, "Longitude": -4.2419424333695845, "DisplayText": "57.480372789947261, -4.2419424333695845"}, "Message": "We\u2019re sorry for the loss of supply. We currently have a fault affecting the areas listed. Our engineers are on site working hard to get the power back on as quickly as they can. If you need more information, please call us on 105 or send us a message on <a href=\"http://m.me/ssencommunity/\">Facebook</a> or Twitter (<a href=\"https://twitter.com/ssencommunity\">@ssencommunity</a>) and quote reference 'HB5871'", "AffectedAreas": ["IV3", "IV3 5LB", "IV3 5LD", "IV3 5LE", "IV3 5LG", "IV3 5LH", "IV3 5LP", "IV3 5LQ", "IV3 5LR", "IV3 8HW"], "DepotCode": "41", "IsDepot": false}, {"Title": "RG2 Area", "Reference": "HB5806", "LoggedAtUtc": "/Date(1618233180000)/", "EstimatedFaultUpdateTimeUtc": "/Date(-62135596800000)/", "EstimatedArrivalOnSiteUtc": "/Date(-62135596800000)/", "EstimatedRestorationTimeUtc": "/Date(1618249200000)/", "FaultType": "LV", "Location": {"Latitude": 51.43071393598084, "Longitude": -0.9698465642339894, "DisplayText": "51.43071393598084, -0.96984656423398941"}, "Message": "We\u2019re sorry for the loss of supply. We currently have a fault affecting the areas listed. Our engineers are on site working hard to get the power back on as quickly as they can. If you need more information, please call us on 105 or send us a message on <a href=\"http://m.me/ssencommunity/\">Facebook</a> or Twitter (<a href=\"https://twitter.com/ssencommunity\">@ssencommunity</a>) and quote reference 'HB5806'", "AffectedAreas": ["RG2 0JH", "RG2 0JN", "RG2 0JQ"], "DepotCode": "49", "IsDepot": false}, {"Title": "RG12 Area", "Reference": "HB5791", "LoggedAtUtc": "/Date(1618230720000)/", "EstimatedFaultUpdateTimeUtc": "/Date(-62135596800000)/", "EstimatedArrivalOnSiteUtc": "/Date(-62135596800000)/", "EstimatedRestorationTimeUtc": "/Date(1618252200000)/", "FaultType": "LV", "Location": {"Latitude": 51.392946652502886, "Longitude": -0.7658777555671489, "DisplayText": "51.392946652502886, -0.76587775556714888"}, "Message": "We\u2019re sorry for the loss of supply. We currently have a fault affecting the areas listed. Our engineers are on site working hard to get the power back on as quickly as they can. If you need more information, please call us on 105 or send us a message on <a href=\"http://m.me/ssencommunity/\">Facebook</a> or Twitter (<a href=\"https://twitter.com/ssencommunity\">@ssencommunity</a>) and quote reference 'HB5791'", "AffectedAreas": ["RG12 7PD", "RG12 7RE", "RG12 7RF"], "DepotCode": "32", "IsDepot": false}, {"Title": "OX5 Area", "Reference": "HB5713", "LoggedAtUtc": "/Date(1618225080000)/", "EstimatedFaultUpdateTimeUtc": "/Date(-62135596800000)/", "EstimatedArrivalOnSiteUtc": "/Date(-62135596800000)/", "EstimatedRestorationTimeUtc": "/Date(1618257600000)/", "FaultType": "LV", "Location": {"Latitude": 51.81644958042644, "Longitude": -1.2842391783623557, "DisplayText": "51.816449580426443, -1.2842391783623557"}, "Message": "We\u2019re sorry for the loss of supply. We currently have a fault affecting the areas listed. Our engineers are on site working hard to get the power back on as quickly as they can. If you need more information, please call us on 105 or send us a message on <a href=\"http://m.me/ssencommunity/\">Facebook</a> or Twitter (<a href=\"https://twitter.com/ssencommunity\">@ssencommunity</a>) and quote reference 'HB5713'", "AffectedAreas": ["OX3 0JH", "OX5 1AY", "OX5 2BP", "OX5 2BT", "OX5 2BU", "OX5 2DH", "OX5 2DL", "OX5 2EH", "OX5 2FW"], "DepotCode": "42", "IsDepot": false}, {"Title": "KY14 Area", "Reference": "HB5639", "LoggedAtUtc": "/Date(1618219500000)/", "EstimatedFaultUpdateTimeUtc": "/Date(-62135596800000)/", "EstimatedArrivalOnSiteUtc": "/Date(-62135596800000)/", "EstimatedRestorationTimeUtc": "/Date(1618243200000)/", "FaultType": "HV", "Location": {"Latitude": 56.30708748081577, "Longitude": -3.3238380578798004, "DisplayText": "56.307087480815767, -3.3238380578798004"}, "Message": "We\u2019re sorry for the loss of supply. We currently have a fault affecting the areas listed. Our engineers are on site working hard to get the power back on as quickly as they can. If you need more information, please call us on 105 or send us a message on <a href=\"http://m.me/ssencommunity/\">Facebook</a> or Twitter (<a href=\"https://twitter.com/ssencommunity\">@ssencommunity</a>) and quote reference 'HB5639'", "AffectedAreas": ["KY14 7RX", "KY14 7RY", "PH2 9PX"], "DepotCode": "70", "IsDepot": false}, {"Title": "SO24 Area", "Reference": "198576", "LoggedAtUtc": "/Date(1618214400000)/", "EstimatedFaultUpdateTimeUtc": "/Date(-62135596800000)/", "EstimatedArrivalOnSiteUtc": "/Date(-62135596800000)/", "EstimatedRestorationTimeUtc": "/Date(1618581600000)/", "FaultType": "PSI", "Location": {"Latitude": 51.08471644701771, "Longitude": -1.1403948629481666, "DisplayText": "51.084716447017712, -1.1403948629481666"}, "Message": "We're sorry for the loss of supply. The reason you're currently without power is a planned outage in the areas listed. We have turned off your electricity supply to allow us to safely carry out essential work to our electrical equipment. By doing this, it'll help us to improve the reliability of our service to you for the future. If you have any questions or require more information, please call us on 105 or send us a message on <a href=\"http://m.me/ssencommunity/\">Facebook</a> or Twitter (<a href=\"https://twitter.com/ssencommunity\">@ssencommunity</a>) with reference  '198576'. You will have received a letter from us confirming your power will be interrupted with specific information relating to your property. If you did not receive this letter, you can assume your power will not be interrupted.", "AffectedAreas": ["SO24 0AA"], "DepotCode": "29", "IsDepot": false}]}