{"Message": "26 reported faults", "TimestampUtc": "/Date(1616595019000)/", "Uri": "http://api.sse.com/powerdistribution/network/v3/api/faults/", "Faults": [{"Title": "RG20 Area", "Reference": "HA6542", "LoggedAtUtc": "/Date(1616594400000)/", "EstimatedFaultUpdateTimeUtc": "/Date(-62135596800000)/", "EstimatedArrivalOnSiteUtc": "/Date(-62135596800000)/", "EstimatedRestorationTimeUtc": "/Date(1616604600000)/", "FaultType": "LV", "Location": {"Latitude": 51.51053746733053, "Longitude": -1.3860188173671124, "DisplayText": "51.510537467330529, -1.3860188173671124"}, "Message": "We\u2019re sorry for the loss of supply. We currently have a fault affecting the areas listed. Our engineers are on site working hard to get the power back on as quickly as they can. If you need more information, please call us on 105 or send us a message on <a href=\"http://m.me/ssencommunity/\">Facebook</a> or Twitter (<a href=\"https://twitter.com/ssencommunity\">@ssencommunity</a>) and quote reference 'HA6542'", "AffectedAreas": ["RG20 7BB", "RG20 7BD", "RG20 7BJ", "RG20 7BL", "RG20 7BN", "RG20 7BP", "RG20 7BU", "RG20 7BW", "RG20 7DH"], "DepotCode": "39", "IsDepot": false}, {"Title": "AB39 Area", "Reference": "HA6705", "LoggedAtUtc": "/Date(1616592720000)/", "EstimatedFaultUpdateTimeUtc": "/Date(-62135596800000)/", "EstimatedArrivalOnSiteUtc": "/Date(-62135596800000)/", "EstimatedRestorationTimeUtc": "/Date(1616603400000)/", "FaultType": "LV", "Location": {"Latitude": 57.03294246193428, "Longitude": -2.1465984031280922, "DisplayText": "57.032942461934283, -2.1465984031280922"}, "Message": "We\u2019re sorry for the loss of supply. We currently have a fault affecting the areas listed. Our engineers are on site working hard to get the power back on as quickly as they can. If you need more information, please call us on 105 or send us a message on <a href=\"http://m.me/ssencommunity/\">Facebook</a> or Twitter (<a href=\"https://twitter.com/ssencommunity\">@ssencommunity</a>) and quote reference 'HA6705'", "AffectedAreas": ["AB39 3BP", "AB39 3NP", "AB39 3TJ", "AB39 3TL", "AB39 3TN", "AB39 3TP", "AB39 3TQ", "AB39 3TR", "AB39 3TU", "AB39 3TX", "AB39 3TY"], "DepotCode": "24", "IsDepot": false}, {"Title": "KW17 Area", "Reference": "198691", "LoggedAtUtc": "/Date(1616592600000)/", "EstimatedFaultUpdateTimeUtc": "/Date(-62135596800000)/", "EstimatedArrivalOnSiteUtc": "/Date(-62135596800000)/", "EstimatedRestorationTimeUtc": "/Date(1616596200000)/", "FaultType": "PSI", "Location": {"Latitude": 59.16200022763358, "Longitude": -2.7674094680162016, "DisplayText": "59.162000227633577, -2.7674094680162016"}, "Message": "We're sorry for the loss of supply. The reason you're currently without power is a planned outage in the areas listed. We have turned off your electricity supply to allow us to safely carry out essential work to our electrical equipment. By doing this, it'll help us to improve the reliability of our service to you for the future. If you have any questions or require more information, please call us on 105 or send us a message on <a href=\"http://m.me/ssencommunity/\">Facebook</a> or Twitter (<a href=\"https://twitter.com/ssencommunity\">@ssencommunity</a>) with reference  '198691'. You will have received a letter from us confirming your power will be interrupted with specific information relating to your property. If you did not receive this letter, you can assume your power will not be interrupted.", "AffectedAreas": ["KW17 2AA"], "DepotCode": "48", "IsDepot": false}, {"Title": "AB33 Area", "Reference": "HA6699", "LoggedAtUtc": "/Date(1616592360000)/", "EstimatedFaultUpdateTimeUtc": "/Date(-62135596800000)/", "EstimatedArrivalOnSiteUtc": "/Date(1616598900000)/", "EstimatedRestorationTimeUtc": "/Date(1616603400000)/", "FaultType": "LV", "Location": {"Latitude": 57.234856757546545, "Longitude": -2.705051308633646, "DisplayText": "57.234856757546545, -2.7050513086336458"}, "Message": "We\u2019re sorry for the loss of supply. We currently have a fault affecting the areas listed. Our engineers are on site working hard to get the power back on as quickly as they can. If you need more information, please call us on 105 or send us a message on <a href=\"http://m.me/ssencommunity/\">Facebook</a> or Twitter (<a href=\"https://twitter.com/ssencommunity\">@ssencommunity</a>) and quote reference 'HA6699'", "AffectedAreas": ["AB33 8AE", "AB33 8AH", "AB33 8QB", "AB33 8QD"], "DepotCode": "24", "IsDepot": false}, {"Title": "SO24 Area", "Reference": "HA6647", "LoggedAtUtc": "/Date(1616588760000)/", "EstimatedFaultUpdateTimeUtc": "/Date(-62135596800000)/", "EstimatedArrivalOnSiteUtc": "/Date(-62135596800000)/", "EstimatedRestorationTimeUtc": "/Date(1616601600000)/", "FaultType": "LV", "Location": {"Latitude": 51.04972625128335, "Longitude": -1.1625562176859001, "DisplayText": "51.049726251283353, -1.1625562176859001"}, "Message": "We\u2019re sorry for the loss of supply. We currently have a fault affecting the areas listed. Our engineers are on site working hard to get the power back on as quickly as they can. If you need more information, please call us on 105 or send us a message on <a href=\"http://m.me/ssencommunity/\">Facebook</a> or Twitter (<a href=\"https://twitter.com/ssencommunity\">@ssencommunity</a>) and quote reference 'HA6647'", "AffectedAreas": ["SO24 0QB", "SO24 0QD", "SO24 0QE", "SO24 0QF", "SO24 0QG"], "DepotCode": "30", "IsDepot": false}, {"Title": "RG21 Area", "Reference": "HA6629", "LoggedAtUtc": "/Date(1616587920000)/", "EstimatedFaultUpdateTimeUtc": "/Date(-62135596800000)/", "EstimatedArrivalOnSiteUtc": "/Date(1616591700000)/", "EstimatedRestorationTimeUtc": "/Date(1616601600000)/", "FaultType": "LV", "Location": {"Latitude": 51.254642530195824, "Longitude": -1.0767163931208028, "DisplayText": "51.254642530195824, -1.0767163931208028"}, "Message": "We\u2019re sorry for the loss of supply. We currently have a fault affecting the areas listed. Our engineers are on site working hard to get the power back on as quickly as they can. If you need more information, please call us on 105 or send us a message on <a href=\"http://m.me/ssencommunity/\">Facebook</a> or Twitter (<a href=\"https://twitter.com/ssencommunity\">@ssencommunity</a>) and quote reference 'HA6629'", "AffectedAreas": ["RG21 3EG", "RG21 3EL"], "DepotCode": "30", "IsDepot": false}, {"Title": "AB41 Area", "Reference": "HA6614", "LoggedAtUtc": "/Date(1616587200000)/", "EstimatedFaultUpdateTimeUtc": "/Date(-62135596800000)/", "EstimatedArrivalOnSiteUtc": "/Date(-62135596800000)/", "EstimatedRestorationTimeUtc": "/Date(1616601600000)/", "FaultType": "HV", "Location": {"Latitude": 57.30394363256209, "Longitude": -2.185633089751572, "DisplayText": "57.303943632562088, -2.1856330897515721"}, "Message": "We\u2019re sorry for the loss of supply. We currently have a fault affecting the areas listed. Our engineers are on site working hard to get the power back on as quickly as they can. If you need more information, please call us on 105 or send us a message on <a href=\"http://m.me/ssencommunity/\">Facebook</a> or Twitter (<a href=\"https://twitter.com/ssencommunity\">@ssencommunity</a>) and quote reference 'HA6614'", "AffectedAreas": ["AB21 0RS", "AB41 6RX", "AB41 6RY", "AB41 6SA", "AB41 6SL", "AB41 6SN", "AB41 6SP"], "DepotCode": "24", "IsDepot": false}, {"Title": "SO45 Area", "Reference": "HA6594", "LoggedAtUtc": "/Date(1616586840000)/", "EstimatedFaultUpdateTimeUtc": "/Date(-62135596800000)/", "EstimatedArrivalOnSiteUtc": "/Date(1616598900000)/", "EstimatedRestorationTimeUtc": "/Date(1616598600000)/", "FaultType": "LV", "Location": {"Latitude": 50.87013990068162, "Longitude": -1.4172900223651124, "DisplayText": "50.870139900681622, -1.4172900223651124"}, "Message": "We\u2019re sorry for the loss of supply. We currently have a fault affecting the areas listed. Our engineers are on site working hard to get the power back on as quickly as they can. If you need more information, please call us on 105 or send us a message on <a href=\"http://m.me/ssencommunity/\">Facebook</a> or Twitter (<a href=\"https://twitter.com/ssencommunity\">@ssencommunity</a>) and quote reference 'HA6594'", "AffectedAreas": ["SO45 5AQ", "SO45 5TA", "SO45 5TB"], "DepotCode": "40", "IsDepot": false}, {"Title": "OX12 & OX5 Areas", "Reference": "HA6700", "LoggedAtUtc": "/Date(1616585400000)/", "EstimatedFaultUpdateTimeUtc": "/Date(-62135596800000)/", "EstimatedArrivalOnSiteUtc": "/Date(-62135596800000)/", "EstimatedRestorationTimeUtc": "/Date(1616605200000)/", "FaultType": "HV", "Location": {"Latitude": 51.80368542043074, "Longitude": -1.254376501498872, "DisplayText": "51.803685420430739, -1.2543765014988719"}, "Message": "We\u2019re sorry for the loss of supply. We currently have a fault affecting the areas listed. Our engineers are on site working hard to get the power back on as quickly as they can. If you need more information, please call us on 105 or send us a message on <a href=\"http://m.me/ssencommunity/\">Facebook</a> or Twitter (<a href=\"https://twitter.com/ssencommunity\">@ssencommunity</a>) and quote reference 'HA6700'", "AffectedAreas": ["OX12 7HN", "OX2 8HA", "OX2 8HD", "OX2 8HE", "OX5 2PU", "OX5 2SB", "OX5 2SD", "OX5 2SG", "OX5 2SU", "OX5 2SX", "OX5 2SY", "OX5 2SZ", "OX5 2TA", "OX5 2TB", "OX5 2TD", "OX5 2TF"], "DepotCode": "42", "IsDepot": false}, {"Title": "HS7 Area", "Reference": "HA6528", "LoggedAtUtc": "/Date(1616583180000)/", "EstimatedFaultUpdateTimeUtc": "/Date(-62135596800000)/", "EstimatedArrivalOnSiteUtc": "/Date(-62135596800000)/", "EstimatedRestorationTimeUtc": "/Date(1616601600000)/", "FaultType": "LV", "Location": {"Latitude": 57.47243461984517, "Longitude": -7.379047149308987, "DisplayText": "57.472434619845167, -7.3790471493089873"}, "Message": "We\u2019re sorry for the loss of supply. We currently have a fault affecting the areas listed. Our engineers are on site working hard to get the power back on as quickly as they can. If you need more information, please call us on 105 or send us a message on <a href=\"http://m.me/ssencommunity/\">Facebook</a> or Twitter (<a href=\"https://twitter.com/ssencommunity\">@ssencommunity</a>) and quote reference 'HA6528'", "AffectedAreas": ["HS7 5AD", "HS7 5LA", "HS7 5LS", "HS7 5LW", "HS7 5NG"], "DepotCode": "52", "IsDepot": false}, {"Title": "GU25 Area", "Reference": "HA5277", "LoggedAtUtc": "/Date(1616581620000)/", "EstimatedFaultUpdateTimeUtc": "/Date(-62135596800000)/", "EstimatedArrivalOnSiteUtc": "/Date(-62135596800000)/", "EstimatedRestorationTimeUtc": "/Date(1616598000000)/", "FaultType": "LV", "Location": {"Latitude": 51.39918570300746, "Longitude": -0.560775192642796, "DisplayText": "51.399185703007461, -0.560775192642796"}, "Message": "We\u2019re sorry for the loss of supply. We currently have a fault affecting the areas listed. Our engineers are on site working hard to get the power back on as quickly as they can. If you need more information, please call us on 105 or send us a message on <a href=\"http://m.me/ssencommunity/\">Facebook</a> or Twitter (<a href=\"https://twitter.com/ssencommunity\">@ssencommunity</a>) and quote reference 'HA5277'", "AffectedAreas": ["GU25 4AZ", "GU25 4BJ", "GU25 4BQ", "GU25 4DQ", "GU25 4DT", "GU25 4DY", "GU25 4SR", "GU25 4SW", "KT16 0EF"], "DepotCode": "32", "IsDepot": false}, {"Title": "SO32 Area", "Reference": "HA6723", "LoggedAtUtc": "/Date(1616581320000)/", "EstimatedFaultUpdateTimeUtc": "/Date(-62135596800000)/", "EstimatedArrivalOnSiteUtc": "/Date(-62135596800000)/", "EstimatedRestorationTimeUtc": "/Date(1616601600000)/", "FaultType": "HV", "Location": {"Latitude": 50.98413159655018, "Longitude": -1.1532656175935763, "DisplayText": "50.984131596550178, -1.1532656175935763"}, "Message": "We\u2019re sorry for the loss of supply. We currently have a fault affecting the areas listed. Our engineers are on site working hard to get the power back on as quickly as they can. If you need more information, please call us on 105 or send us a message on <a href=\"http://m.me/ssencommunity/\">Facebook</a> or Twitter (<a href=\"https://twitter.com/ssencommunity\">@ssencommunity</a>) and quote reference 'HA6723'", "AffectedAreas": ["SO32 3LL"], "DepotCode": "40", "IsDepot": false}, {"Title": "UB7 Area", "Reference": "HA6130", "LoggedAtUtc": "/Date(1616581200000)/", "EstimatedFaultUpdateTimeUtc": "/Date(-62135596800000)/", "EstimatedArrivalOnSiteUtc": "/Date(-62135596800000)/", "EstimatedRestorationTimeUtc": "/Date(1616598600000)/", "FaultType": "LV", "Location": {"Latitude": 51.48252463454809, "Longitude": -0.47188704761798156, "DisplayText": "51.482524634548092, -0.47188704761798156"}, "Message": "We\u2019re sorry for the loss of supply. We currently have a fault affecting the areas listed. Our engineers are on site working hard to get the power back on as quickly as they can. If you need more information, please call us on 105 or send us a message on <a href=\"http://m.me/ssencommunity/\">Facebook</a> or Twitter (<a href=\"https://twitter.com/ssencommunity\">@ssencommunity</a>) and quote reference 'HA6130'", "AffectedAreas": ["UB7 0DE", "UB7 0DH", "UB7 0DJ", "UB7 0DL", "UB7 0DQ", "UB7 0EP"], "DepotCode": "36", "IsDepot": false}, {"Title": "OX44 Area", "Reference": "HA6589", "LoggedAtUtc": "/Date(1616578440000)/", "EstimatedFaultUpdateTimeUtc": "/Date(-62135596800000)/", "EstimatedArrivalOnSiteUtc": "/Date(-62135596800000)/", "EstimatedRestorationTimeUtc": "/Date(1616605200000)/", "FaultType": "HV", "Location": {"Latitude": 51.71592713271436, "Longitude": -1.1504856701437096, "DisplayText": "51.715927132714363, -1.1504856701437096"}, "Message": "We\u2019re sorry for the loss of supply. We currently have a fault affecting the areas listed. Our engineers are on site working hard to get the power back on as quickly as they can. If you need more information, please call us on 105 or send us a message on <a href=\"http://m.me/ssencommunity/\">Facebook</a> or Twitter (<a href=\"https://twitter.com/ssencommunity\">@ssencommunity</a>) and quote reference 'HA6589'", "AffectedAreas": ["OX44 9DD", "OX44 9JL"], "DepotCode": "42", "IsDepot": false}, {"Title": "PA37 Area", "Reference": "197872", "LoggedAtUtc": "/Date(1616578200000)/", "EstimatedFaultUpdateTimeUtc": "/Date(-62135596800000)/", "EstimatedArrivalOnSiteUtc": "/Date(-62135596800000)/", "EstimatedRestorationTimeUtc": "/Date(1616596200000)/", "FaultType": "PSI", "Location": {"Latitude": 56.46723407354828, "Longitude": -5.3558289040756195, "DisplayText": "56.467234073548283, -5.3558289040756195"}, "Message": "We're sorry for the loss of supply. The reason you're currently without power is a planned outage in the areas listed. We have turned off your electricity supply to allow us to safely carry out essential work to our electrical equipment. By doing this, it'll help us to improve the reliability of our service to you for the future. If you have any questions or require more information, please call us on 105 or send us a message on <a href=\"http://m.me/ssencommunity/\">Facebook</a> or Twitter (<a href=\"https://twitter.com/ssencommunity\">@ssencommunity</a>) with reference  '197872'. You will have received a letter from us confirming your power will be interrupted with specific information relating to your property. If you did not receive this letter, you can assume your power will not be interrupted.", "AffectedAreas": ["PA37 1QX", "PA37 1QZ", "PA37 1RA", "PA37 1RD", "PA37 1RE", "PA37 1RG", "PA37 1RX", "PA37 1TD"], "DepotCode": "57", "IsDepot": false}, {"Title": "AB45 Area", "Reference": "197849", "LoggedAtUtc": "/Date(1616576400000)/", "EstimatedFaultUpdateTimeUtc": "/Date(-62135596800000)/", "EstimatedArrivalOnSiteUtc": "/Date(-62135596800000)/", "EstimatedRestorationTimeUtc": "/Date(1616598000000)/", "FaultType": "PSI", "Location": {"Latitude": 57.671615696843936, "Longitude": -2.689737719293664, "DisplayText": "57.671615696843936, -2.6897377192936638"}, "Message": "We're sorry for the loss of supply. The reason you're currently without power is a planned outage in the areas listed. We have turned off your electricity supply to allow us to safely carry out essential work to our electrical equipment. By doing this, it'll help us to improve the reliability of our service to you for the future. If you have any questions or require more information, please call us on 105 or send us a message on <a href=\"http://m.me/ssencommunity/\">Facebook</a> or Twitter (<a href=\"https://twitter.com/ssencommunity\">@ssencommunity</a>) with reference  '197849'. You will have received a letter from us confirming your power will be interrupted with specific information relating to your property. If you did not receive this letter, you can assume your power will not be interrupted.", "AffectedAreas": ["AB45 2XT", "AB45 2XX"], "DepotCode": "24", "IsDepot": false}, {"Title": "SO32 Area", "Reference": "197972", "LoggedAtUtc": "/Date(1616576400000)/", "EstimatedFaultUpdateTimeUtc": "/Date(-62135596800000)/", "EstimatedArrivalOnSiteUtc": "/Date(-62135596800000)/", "EstimatedRestorationTimeUtc": "/Date(1616601600000)/", "FaultType": "PSI", "Location": {"Latitude": 50.93627044498044, "Longitude": -1.2119292870548546, "DisplayText": "50.936270444980437, -1.2119292870548546"}, "Message": "We're sorry for the loss of supply. The reason you're currently without power is a planned outage in the areas listed. We have turned off your electricity supply to allow us to safely carry out essential work to our electrical equipment. By doing this, it'll help us to improve the reliability of our service to you for the future. If you have any questions or require more information, please call us on 105 or send us a message on <a href=\"http://m.me/ssencommunity/\">Facebook</a> or Twitter (<a href=\"https://twitter.com/ssencommunity\">@ssencommunity</a>) with reference  '197972'. You will have received a letter from us confirming your power will be interrupted with specific information relating to your property. If you did not receive this letter, you can assume your power will not be interrupted.", "AffectedAreas": ["SO32 1DR", "SO32 2BH", "SO32 2LD", "SO32 2LE", "SO32 2LN", "SO32 2LQ", "SO32 2LR"], "DepotCode": "40", "IsDepot": false}, {"Title": "RG25 Area", "Reference": "198388", "LoggedAtUtc": "/Date(1616576400000)/", "EstimatedFaultUpdateTimeUtc": "/Date(-62135596800000)/", "EstimatedArrivalOnSiteUtc": "/Date(-62135596800000)/", "EstimatedRestorationTimeUtc": "/Date(1616601600000)/", "FaultType": "PSI", "Location": {"Latitude": 51.170647940854025, "Longitude": -1.132075952443227, "DisplayText": "51.170647940854025, -1.1320759524432269"}, "Message": "We're sorry for the loss of supply. The reason you're currently without power is a planned outage in the areas listed. We have turned off your electricity supply to allow us to safely carry out essential work to our electrical equipment. By doing this, it'll help us to improve the reliability of our service to you for the future. If you have any questions or require more information, please call us on 105 or send us a message on <a href=\"http://m.me/ssencommunity/\">Facebook</a> or Twitter (<a href=\"https://twitter.com/ssencommunity\">@ssencommunity</a>) with reference  '198388'. You will have received a letter from us confirming your power will be interrupted with specific information relating to your property. If you did not receive this letter, you can assume your power will not be interrupted.", "AffectedAreas": ["RG25 2EF", "RG25 2EH", "RG25 2ET", "RG25 2EZ"], "DepotCode": "44", "IsDepot": false}, {"Title": "KW12 Area", "Reference": "198266", "LoggedAtUtc": "/Date(1616576400000)/", "EstimatedFaultUpdateTimeUtc": "/Date(-62135596800000)/", "EstimatedArrivalOnSiteUtc": "/Date(-62135596800000)/", "EstimatedRestorationTimeUtc": "/Date(1616598000000)/", "FaultType": "PSI", "Location": {"Latitude": 58.49198578754763, "Longitude": -3.478350599229083, "DisplayText": "58.491985787547627, -3.4783505992290831"}, "Message": "We're sorry for the loss of supply. The reason you're currently without power is a planned outage in the areas listed. We have turned off your electricity supply to allow us to safely carry out essential work to our electrical equipment. By doing this, it'll help us to improve the reliability of our service to you for the future. If you have any questions or require more information, please call us on 105 or send us a message on <a href=\"http://m.me/ssencommunity/\">Facebook</a> or Twitter (<a href=\"https://twitter.com/ssencommunity\">@ssencommunity</a>) with reference  '198266'. You will have received a letter from us confirming your power will be interrupted with specific information relating to your property. If you did not receive this letter, you can assume your power will not be interrupted.", "AffectedAreas": ["KW1 4HG", "KW12 6XJ", "KW12 6YW", "KW14 7QZ"], "DepotCode": "41", "IsDepot": false}, {"Title": "AB13 & AB15 Areas", "Reference": "197808", "LoggedAtUtc": "/Date(1616576400000)/", "EstimatedFaultUpdateTimeUtc": "/Date(-62135596800000)/", "EstimatedArrivalOnSiteUtc": "/Date(-62135596800000)/", "EstimatedRestorationTimeUtc": "/Date(1616598000000)/", "FaultType": "PSI", "Location": {"Latitude": 57.1137432774117, "Longitude": -2.216497111566034, "DisplayText": "57.1137432774117, -2.2164971115660341"}, "Message": "We're sorry for the loss of supply. The reason you're currently without power is a planned outage in the areas listed. We have turned off your electricity supply to allow us to safely carry out essential work to our electrical equipment. By doing this, it'll help us to improve the reliability of our service to you for the future. If you have any questions or require more information, please call us on 105 or send us a message on <a href=\"http://m.me/ssencommunity/\">Facebook</a> or Twitter (<a href=\"https://twitter.com/ssencommunity\">@ssencommunity</a>) with reference  '197808'. You will have received a letter from us confirming your power will be interrupted with specific information relating to your property. If you did not receive this letter, you can assume your power will not be interrupted.", "AffectedAreas": ["AB13 0HS", "AB13 0HX", "AB15 9EB", "AB15 9EJ", "AB15 9EL"], "DepotCode": "24", "IsDepot": false}, {"Title": "IV30 Area", "Reference": "198741", "LoggedAtUtc": "/Date(1616576400000)/", "EstimatedFaultUpdateTimeUtc": "/Date(-62135596800000)/", "EstimatedArrivalOnSiteUtc": "/Date(-62135596800000)/", "EstimatedRestorationTimeUtc": "/Date(1616599800000)/", "FaultType": "PSI", "Location": {"Latitude": 57.633073910621334, "Longitude": -3.328711954900863, "DisplayText": "57.633073910621334, -3.328711954900863"}, "Message": "We're sorry for the loss of supply. The reason you're currently without power is a planned outage in the areas listed. We have turned off your electricity supply to allow us to safely carry out essential work to our electrical equipment. By doing this, it'll help us to improve the reliability of our service to you for the future. If you have any questions or require more information, please call us on 105 or send us a message on <a href=\"http://m.me/ssencommunity/\">Facebook</a> or Twitter (<a href=\"https://twitter.com/ssencommunity\">@ssencommunity</a>) with reference  '198741'. You will have received a letter from us confirming your power will be interrupted with specific information relating to your property. If you did not receive this letter, you can assume your power will not be interrupted.", "AffectedAreas": ["IV30 8RS"], "DepotCode": "24", "IsDepot": false}, {"Title": "AB51 Area", "Reference": "HA6428", "LoggedAtUtc": "/Date(1616575560000)/", "EstimatedFaultUpdateTimeUtc": "/Date(-62135596800000)/", "EstimatedArrivalOnSiteUtc": "/Date(-62135596800000)/", "EstimatedRestorationTimeUtc": "/Date(1616599800000)/", "FaultType": "HV", "Location": {"Latitude": 57.376888311839906, "Longitude": -2.50492439792694, "DisplayText": "57.376888311839906, -2.50492439792694"}, "Message": "We\u2019re sorry for the loss of supply. We currently have a fault affecting the areas listed. Our engineers are on site working hard to get the power back on as quickly as they can. If you need more information, please call us on 105 or send us a message on <a href=\"http://m.me/ssencommunity/\">Facebook</a> or Twitter (<a href=\"https://twitter.com/ssencommunity\">@ssencommunity</a>) and quote reference 'HA6428'", "AffectedAreas": ["AB51 5AE", "AB51 5AQ", "AB51 5BR", "AB51 5BS", "AB51 5DE", "AB51 5DH", "AB52 6US"], "DepotCode": "24", "IsDepot": false}, {"Title": "GL54 Area", "Reference": "197795", "LoggedAtUtc": "/Date(1616574600000)/", "EstimatedFaultUpdateTimeUtc": "/Date(-62135596800000)/", "EstimatedArrivalOnSiteUtc": "/Date(-62135596800000)/", "EstimatedRestorationTimeUtc": "/Date(1616601600000)/", "FaultType": "PSI", "Location": {"Latitude": 51.88222653581424, "Longitude": -1.726739586420866, "DisplayText": "51.88222653581424, -1.7267395864208659"}, "Message": "We're sorry for the loss of supply. The reason you're currently without power is a planned outage in the areas listed. We have turned off your electricity supply to allow us to safely carry out essential work to our electrical equipment. By doing this, it'll help us to improve the reliability of our service to you for the future. If you have any questions or require more information, please call us on 105 or send us a message on <a href=\"http://m.me/ssencommunity/\">Facebook</a> or Twitter (<a href=\"https://twitter.com/ssencommunity\">@ssencommunity</a>) with reference  '197795'. You will have received a letter from us confirming your power will be interrupted with specific information relating to your property. If you did not receive this letter, you can assume your power will not be interrupted.", "AffectedAreas": ["GL54 2HQ", "GL54 2NB", "GL54 2ND", "GL54 2NE"], "DepotCode": "42", "IsDepot": false}, {"Title": "SO24 Area", "Reference": "198059", "LoggedAtUtc": "/Date(1616574600000)/", "EstimatedFaultUpdateTimeUtc": "/Date(-62135596800000)/", "EstimatedArrivalOnSiteUtc": "/Date(-62135596800000)/", "EstimatedRestorationTimeUtc": "/Date(1616605200000)/", "FaultType": "PSI", "Location": {"Latitude": 51.08489246277394, "Longitude": -1.08422510367185, "DisplayText": "51.084892462773936, -1.08422510367185"}, "Message": "We're sorry for the loss of supply. The reason you're currently without power is a planned outage in the areas listed. We have turned off your electricity supply to allow us to safely carry out essential work to our electrical equipment. By doing this, it'll help us to improve the reliability of our service to you for the future. If you have any questions or require more information, please call us on 105 or send us a message on <a href=\"http://m.me/ssencommunity/\">Facebook</a> or Twitter (<a href=\"https://twitter.com/ssencommunity\">@ssencommunity</a>) with reference  '198059'. You will have received a letter from us confirming your power will be interrupted with specific information relating to your property. If you did not receive this letter, you can assume your power will not be interrupted.", "AffectedAreas": ["SO24 0BT", "SO24 0BU", "SO24 0DS", "SO24 0DU"], "DepotCode": "44", "IsDepot": false}, {"Title": "GU24 & GU25 Areas", "Reference": "197773", "LoggedAtUtc": "/Date(1616572800000)/", "EstimatedFaultUpdateTimeUtc": "/Date(-62135596800000)/", "EstimatedArrivalOnSiteUtc": "/Date(-62135596800000)/", "EstimatedRestorationTimeUtc": "/Date(1616601600000)/", "FaultType": "PSI", "Location": {"Latitude": 51.37625607411952, "Longitude": -0.6092256392988282, "DisplayText": "51.376256074119517, -0.60922563929882823"}, "Message": "We're sorry for the loss of supply. The reason you're currently without power is a planned outage in the areas listed. We have turned off your electricity supply to allow us to safely carry out essential work to our electrical equipment. By doing this, it'll help us to improve the reliability of our service to you for the future. If you have any questions or require more information, please call us on 105 or send us a message on <a href=\"http://m.me/ssencommunity/\">Facebook</a> or Twitter (<a href=\"https://twitter.com/ssencommunity\">@ssencommunity</a>) with reference  '197773'. You will have received a letter from us confirming your power will be interrupted with specific information relating to your property. If you did not receive this letter, you can assume your power will not be interrupted.", "AffectedAreas": ["GU24 8SJ", "GU25 4NA", "GU25 4ND"], "DepotCode": "53", "IsDepot": false}, {"Title": "GL54 Area", "Reference": "197796", "LoggedAtUtc": "/Date(1616493600000)/", "EstimatedFaultUpdateTimeUtc": "/Date(-62135596800000)/", "EstimatedArrivalOnSiteUtc": "/Date(-62135596800000)/", "EstimatedRestorationTimeUtc": "/Date(1616670000000)/", "FaultType": "PSI", "Location": {"Latitude": 51.870024327591686, "Longitude": -1.722238375286941, "DisplayText": "51.870024327591686, -1.722238375286941"}, "Message": "We're sorry for the loss of supply. The reason you're currently without power is a planned outage in the areas listed. We have turned off your electricity supply to allow us to safely carry out essential work to our electrical equipment. By doing this, it'll help us to improve the reliability of our service to you for the future. If you have any questions or require more information, please call us on 105 or send us a message on <a href=\"http://m.me/ssencommunity/\">Facebook</a> or Twitter (<a href=\"https://twitter.com/ssencommunity\">@ssencommunity</a>) with reference  '197796'. You will have received a letter from us confirming your power will be interrupted with specific information relating to your property. If you did not receive this letter, you can assume your power will not be interrupted.", "AffectedAreas": ["GL54 2LN", "GL54 2NA", "GL54 2NB", "GL54 2ND"], "DepotCode": "42", "IsDepot": false}]}